pivottablejs/__init__.py
pivottablejs-0.9.0.dist-info/DESCRIPTION.rst
pivottablejs-0.9.0.dist-info/METADATA
pivottablejs-0.9.0.dist-info/RECORD
pivottablejs-0.9.0.dist-info/WHEEL
pivottablejs-0.9.0.dist-info/metadata.json
pivottablejs-0.9.0.dist-info/top_level.txt
