Metadata-Version: 1.1
Name: pivottablejs
Version: 0.9.0
Summary: PivotTable.js integration for Jupyter/IPython Notebook
Home-page: https://github.com/nicolaskruchten/jupyter_pivottablejs
Author: Nicolas Kruchten
Author-email: nicolas@kruchten.com
License: MIT
Keywords: pivot table grid pivottable pivotgrid pivotchart crosstab
Platform: UNKNOWN
Classifier: Development Status :: 4 - Beta
Classifier: Intended Audience :: Developers
Classifier: Intended Audience :: Science/Research
Classifier: Intended Audience :: End Users/Desktop
Classifier: Topic :: Scientific/Engineering :: Information Analysis
Classifier: Topic :: Scientific/Engineering :: Visualization
Classifier: Topic :: Utilities
Classifier: Environment :: Web Environment
Classifier: Framework :: IPython
Classifier: License :: OSI Approved :: MIT License
Classifier: Programming Language :: Python :: 2
Classifier: Programming Language :: Python :: 3
Classifier: Programming Language :: JavaScript
